hoy/__init__.py
hoy/hoy.py
hoy-1.0.6.dist-info/METADATA
hoy-1.0.6.dist-info/WHEEL
hoy-1.0.6.dist-info/entry_points.txt
hoy-1.0.6.dist-info/licenses/LICENSE
hoy-1.0.6.dist-info/RECORD
