Metadata-Version: 2.4
Name: hoy
Version: 1.0.6
Summary: A dead simple notifier.
Project-URL: Documentation, https://github.com/lezgomatt/hoy#readme
Project-URL: Issues, https://github.com/lezgomatt/hoy/issues
Project-URL: Source, https://github.com/lezgomatt/hoy
Author-email: Matthew Go <lezgomatt@gmail.com>
License-Expression: Zlib
License-File: LICENSE
Classifier: Development Status :: 5 - Production/Stable
Classifier: Intended Audience :: System Administrators
Classifier: License :: OSI Approved :: zlib/libpng License
Classifier: Operating System :: MacOS
Classifier: Operating System :: Microsoft :: Windows
Classifier: Operating System :: POSIX :: Linux
Classifier: Programming Language :: Python :: 3
Classifier: Topic :: Utilities
Classifier: Typing :: Typed
Requires-Python: >=3.9
